airflask/__init__.py
airflask/__main__.py
airflask/deploy.py
airflask-0.9.10.dist-info/licenses/LICENSE
airflask-0.9.10.dist-info/METADATA
airflask-0.9.10.dist-info/WHEEL
airflask-0.9.10.dist-info/entry_points.txt
airflask-0.9.10.dist-info/top_level.txt
airflask-0.9.10.dist-info/RECORD
