Metadata-Version: 2.4
Name: airflask
Version: 0.9.10
Summary: Simplest way to host your flask web app in production!
Author: Naitik Mundra
Author-email: naitikmundra18@gmail.com
License: MIT
Project-URL: GitHub Repository, https://github.com/naitikmundra/AirFlask
License-File: LICENSE
Requires-Dist: flask
Requires-Dist: click
Requires-Dist: psutil
Requires-Dist: gevent
Dynamic: author
Dynamic: author-email
Dynamic: description
Dynamic: description-content-type
Dynamic: license
Dynamic: license-file
Dynamic: project-url
Dynamic: requires-dist
Dynamic: summary
